mymi/__init__.py
mymi-0.0.1.dist-info/METADATA
mymi-0.0.1.dist-info/WHEEL
mymi-0.0.1.dist-info/top_level.txt
mymi-0.0.1.dist-info/RECORD
