Metadata-Version: 2.1
Name: mymi
Version: 0.0.1
Summary: Medical imaging code
Home-page: https://github.com/clarkbab/medical-imaging
Author: Brett Clark
Author-email: clarkbab@gmail.com
License: UNKNOWN
Keywords: medical imaging
Platform: UNKNOWN
